TileStache/Caches.py
TileStache/Config.py
TileStache/Core.py
TileStache/Geography.py
TileStache/MBTiles.py
TileStache/Mapnik.py
TileStache/Memcache.py
TileStache/PixelEffects.py
TileStache/Pixels.py
TileStache/Providers.py
TileStache/Redis.py
TileStache/S3.py
TileStache/Sandwich.py
TileStache/VERSION
TileStache/__init__.py
TileStache/Goodies/AreaServer.py
TileStache/Goodies/ExternalConfigServer.py
TileStache/Goodies/Proj4Projection.py
TileStache/Goodies/StatusServer.py
TileStache/Goodies/__init__.py
TileStache/Goodies/Caches/GoogleCloud.py
TileStache/Goodies/Caches/LimitedDisk.py
TileStache/Goodies/Caches/__init__.py
TileStache/Goodies/Providers/Cascadenik.py
TileStache/Goodies/Providers/Composite.py
TileStache/Goodies/Providers/GDAL.py
TileStache/Goodies/Providers/Grid.py
TileStache/Goodies/Providers/MapnikGrid.py
TileStache/Goodies/Providers/MirrorOSM.py
TileStache/Goodies/Providers/Monkeycache.py
TileStache/Goodies/Providers/PostGeoJSON.py
TileStache/Goodies/Providers/SolrGeoJSON.py
TileStache/Goodies/Providers/TileDataOSM.py
TileStache/Goodies/Providers/UtfGridComposite.py
TileStache/Goodies/Providers/UtfGridCompositeOverlap.py
TileStache/Goodies/Providers/__init__.py
TileStache/Goodies/VecTiles/__init__.py
TileStache/Goodies/VecTiles/client.py
TileStache/Goodies/VecTiles/geojson.py
TileStache/Goodies/VecTiles/mvt.py
TileStache/Goodies/VecTiles/ops.py
TileStache/Goodies/VecTiles/pbf.py
TileStache/Goodies/VecTiles/server.py
TileStache/Goodies/VecTiles/topojson.py
TileStache/Goodies/VecTiles/wkb.py
TileStache/Vector/Arc.py
TileStache/Vector/__init__.py
TileStache-1.51.6.data/data/share/tilestache/DejaVuSansMono-alphanumeric.ttf
TileStache-1.51.6.data/scripts/tilestache-clean.py
TileStache-1.51.6.data/scripts/tilestache-compose.py
TileStache-1.51.6.data/scripts/tilestache-list.py
TileStache-1.51.6.data/scripts/tilestache-render.py
TileStache-1.51.6.data/scripts/tilestache-seed.py
TileStache-1.51.6.dist-info/DESCRIPTION.rst
TileStache-1.51.6.dist-info/METADATA
TileStache-1.51.6.dist-info/RECORD
TileStache-1.51.6.dist-info/WHEEL
TileStache-1.51.6.dist-info/metadata.json
TileStache-1.51.6.dist-info/top_level.txt
