Metadata-Version: 2.0
Name: TileStache
Version: 1.51.6
Summary: A stylish alternative for caching your map tiles.
Home-page: http://tilestache.org
Author: Michal Migurski
Author-email: mike@stamen.com
License: BSD
Platform: UNKNOWN
Requires-Dist: ModestMaps (>=1.3.0)
Requires-Dist: simplejson
Requires-Dist: Werkzeug (==0.11.13)
Requires-Dist: Pillow
